wunderpy2/__init__.py
wunderpy2/endpoint_helpers.py
wunderpy2/exceptions.py
wunderpy2/lists_endpoint.py
wunderpy2/model.py
wunderpy2/notes_endpoint.py
wunderpy2/positions_endpoints.py
wunderpy2/subtasks_endpoint.py
wunderpy2/tasks_endpoint.py
wunderpy2/wunderapi.py
wunderpy2/wunderclient.py
wunderpy2-0.1.6.dist-info/DESCRIPTION.rst
wunderpy2-0.1.6.dist-info/METADATA
wunderpy2-0.1.6.dist-info/RECORD
wunderpy2-0.1.6.dist-info/WHEEL
wunderpy2-0.1.6.dist-info/metadata.json
wunderpy2-0.1.6.dist-info/top_level.txt
