Metadata-Version: 2.0
Name: wunderpy2
Version: 0.1.6
Summary: A Python library for the Wunderlist 2 REST API
Home-page: https://github.com/mieubrisse/wunderpy2
Author: mieubrisse
Author-email: mieubrisse@gmail.com
License: MIT
Keywords: wunderpy wunderpy2 wunderlist api cli
Platform: UNKNOWN
Classifier: Development Status :: 3 - Alpha
Classifier: Intended Audience :: Developers
Classifier: Topic :: Software Development :: Libraries
Classifier: Topic :: Software Development :: Libraries :: Python Modules
Classifier: Topic :: Utilities
Classifier: Natural Language :: English
Classifier: License :: OSI Approved :: MIT License
Classifier: Programming Language :: Python :: 2.7
Classifier: Programming Language :: Python :: 3
Classifier: Programming Language :: Python :: 3.2
Classifier: Programming Language :: Python :: 3.3
Classifier: Programming Language :: Python :: 3.4
Requires-Dist: requests
